README
setup.py
d3/__init__.py
d3/main.py
d3.egg-info/PKG-INFO
d3.egg-info/SOURCES.txt
d3.egg-info/dependency_links.txt
d3.egg-info/top_level.txt