Metadata-Version: 1.0
Name: d3
Version: 0.1.0
Summary: A D3.js programming API for python
Home-page: https://github.com/yuhangwang/d3-python
Author: Yuhang(Steven) Wang
Author-email: UNKNOWN
License: MIT/X11
Platform: UNKNOWN
